datahelper/__init__.py
datahelper/core/processor.py
datahelper/core/reader.py
xiaoming_datahelper-0.1.3.dist-info/METADATA
xiaoming_datahelper-0.1.3.dist-info/WHEEL
xiaoming_datahelper-0.1.3.dist-info/top_level.txt
xiaoming_datahelper-0.1.3.dist-info/RECORD
