Metadata-Version: 2.4
Name: xiaoming-datahelper
Version: 0.1.3
Summary: 一个简单的数据处理工具包
Author-email: 小明 <xiaoming@example.com>
License-Expression: MIT
Project-URL: Homepage, https://github.com/examples/xiaoming-datahelper
Classifier: Programming Language :: Python :: 3
Classifier: Operating System :: OS Independent
Requires-Python: >=3.9
Requires-Dist: pandas>=1.0.0
Requires-Dist: numpy>=1.18.0
Provides-Extra: dev
Requires-Dist: pytest>=6.0; extra == "dev"
Requires-Dist: black>=21.0; extra == "dev"
